setup.py
tic_tac_toe/__init__.py
tic_tac_toe/tic_tac_toe.py
tic_tac_toe.egg-info/PKG-INFO
tic_tac_toe.egg-info/SOURCES.txt
tic_tac_toe.egg-info/dependency_links.txt
tic_tac_toe.egg-info/entry_points.txt
tic_tac_toe.egg-info/requires.txt
tic_tac_toe.egg-info/top_level.txt