Metadata-Version: 1.0
Name: tic-tac-toe
Version: 0.1.0
Summary: Command Line TicTacToe with win/loss/draw prediction per box, per move
Home-page: https://github.com/HusainZafar/tic_tac_toe
Author: Husain Zafar
Author-email: husainzafar1996@gmail.com
License: MIT
Platform: UNKNOWN
